{
  "id" : 4711,
  "ident" : {
    "airline" : "DLH",
    "reg" : "D-EVEL",
    "call" : "DLH1234"
  },
  "type" : {
    "icao" : "C172",
    "wingSpan" : 11.1,
    "wingArea" : 16.2
  },
  "position" : {
    "lat" : 51.406292,
    "lon" : 6.939847,
    "alt_geo" : 407,
    "gnd" : true
  },
  "attitude" : {
    "roll" : -0.2,
    "heading" : 42,
    "pitch" : 0.1
  },
  "config" : {
    "mass" : 1037.6,
    "lift" : 10178.86,
    "gear" : 1,
    "noseWheel" : -2.5,
    "flaps" : 0.5,
    "spoiler" : 0
  },
  "light" : {
    "taxi" : true,
    "landing" : false,
    "beacon" : true,
    "strobe" : false,
    "nac" : true
  }
}